commonroad_openscenario_converter-0.1.1.data/data/LICENSE
osc_cr_converter/__init__.py
osc_cr_converter/analyzer/__init__.py
osc_cr_converter/analyzer/base.py
osc_cr_converter/analyzer/enum_analyzer.py
osc_cr_converter/analyzer/error.py
osc_cr_converter/analyzer/result.py
osc_cr_converter/batch/__init__.py
osc_cr_converter/batch/analysis.py
osc_cr_converter/batch/converter.py
osc_cr_converter/converter/__init__.py
osc_cr_converter/converter/base.py
osc_cr_converter/converter/osc2cr.py
osc_cr_converter/converter/result.py
osc_cr_converter/converter/serializable.py
osc_cr_converter/udp_driver/__init__.py
osc_cr_converter/udp_driver/common.py
osc_cr_converter/utility/__init__.py
osc_cr_converter/utility/abs_rel.py
osc_cr_converter/utility/configuration.py
osc_cr_converter/utility/general.py
osc_cr_converter/utility/logger.py
osc_cr_converter/utility/obstacle_info.py
osc_cr_converter/utility/pps_builder.py
osc_cr_converter/utility/statistics.py
osc_cr_converter/utility/visualization.py
osc_cr_converter/wrapper/__init__.py
osc_cr_converter/wrapper/base/__init__.py
osc_cr_converter/wrapper/base/ending_cause.py
osc_cr_converter/wrapper/base/scenario_object.py
osc_cr_converter/wrapper/base/sim_wrapper.py
osc_cr_converter/wrapper/esmini/__init__.py
osc_cr_converter/wrapper/esmini/esmini_scenario_object.py
osc_cr_converter/wrapper/esmini/esmini_wrapper.py
osc_cr_converter/wrapper/esmini/esmini_wrapper_provider.py
osc_cr_converter/wrapper/esmini/storyboard_element.py
tests/__init__.py
tests/test_conversion.py
commonroad_openscenario_converter-0.1.1.dist-info/LICENSE
commonroad_openscenario_converter-0.1.1.dist-info/METADATA
commonroad_openscenario_converter-0.1.1.dist-info/WHEEL
commonroad_openscenario_converter-0.1.1.dist-info/top_level.txt
commonroad_openscenario_converter-0.1.1.dist-info/RECORD
