Metadata-Version: 2.1
Name: commonroad-openscenario-converter
Version: 0.1.1
Summary: Converter between OpenSCENARIO and CommonRoad formats
Home-page: https://commonroad.in.tum.de/tools/openscenario-converter
Author: Yuanfei Lin, Michael Ratzel, Matthias Althoff
Author-email: yuanfei.lin@tum.de
License: BSD 3-Clause
Project-URL: Documentation, https://cps.pages.gitlab.lrz.de/commonroad/commonroad-openscenario-converter/
Project-URL: Forum, https://commonroad.in.tum.de/forum/c/dataset-converter/
Project-URL: Source, https://gitlab.lrz.de/tum-cps/commonroad-openscenario-converter
Keywords: scenario description,autonomous driving
Classifier: Programming Language :: Python :: 3.9
Classifier: Programming Language :: Python :: 3.10
Classifier: Programming Language :: Python :: 3.11
Classifier: License :: OSI Approved :: BSD License
Classifier: Operating System :: POSIX :: Linux
License-File: LICENSE
Requires-Dist: commonroad-io>=2024.2
Requires-Dist: commonroad-scenario-designer>=0.8.2
Requires-Dist: imageio>=2.28.1
Requires-Dist: numpy>=1.19.0
Requires-Dist: tqdm>=4.65.0
Requires-Dist: scenariogeneration>=0.9.0
Provides-Extra: tests
Requires-Dist: pytest>=7.1; extra == "tests"
